pusher/__init__.py
pusher/aiohttp.py
pusher/authentication_client.py
pusher/cacert.pem
pusher/client.py
pusher/crypto.py
pusher/errors.py
pusher/gae.py
pusher/http.py
pusher/pusher.py
pusher/pusher_client.py
pusher/requests.py
pusher/signature.py
pusher/tornado.py
pusher/util.py
pusher/version.py
pusher-3.3.3.dist-info/LICENSE
pusher-3.3.3.dist-info/METADATA
pusher-3.3.3.dist-info/WHEEL
pusher-3.3.3.dist-info/top_level.txt
pusher-3.3.3.dist-info/RECORD
