Metadata-Version: 2.1
Name: pusher
Version: 3.3.3
Summary: A Python library to interract with the Pusher Channels API
Home-page: https://github.com/pusher/pusher-http-python
Author: Pusher
Author-email: support@pusher.com
License: MIT
Keywords: pusher rest realtime websockets service
Classifier: License :: OSI Approved :: MIT License
Classifier: Programming Language :: Python
Classifier: Development Status :: 4 - Beta
Classifier: Intended Audience :: Developers
Classifier: Topic :: Internet :: WWW/HTTP
Classifier: Programming Language :: Python :: 2
Classifier: Programming Language :: Python :: 3
Provides-Extra: aiohttp
Provides-Extra: tornado
License-File: LICENSE
